marshmallow_dataclass_djangofield/__init__.py
marshmallow_dataclass_djangofield-0.4.0.dist-info/METADATA
marshmallow_dataclass_djangofield-0.4.0.dist-info/LICENSE
marshmallow_dataclass_djangofield-0.4.0.dist-info/WHEEL
marshmallow_dataclass_djangofield-0.4.0.dist-info/RECORD
