Metadata-Version: 2.1
Name: marshmallow-dataclass-djangofield
Version: 0.4.0
Summary: Use marshmallow-dataclass as a Django Field
Home-page: https://github.com/OJFord/marshmallow-dataclass-djangofield
License: MIT
Keywords: Django,database,marshmallow
Author: Oliver Ford
Author-email: dev@ojford.com
Requires-Python: >=3.7
Classifier: Framework :: Django
Classifier: License :: OSI Approved :: MIT License
Classifier: Programming Language :: Python :: 3
Classifier: Programming Language :: Python :: 3.7
Classifier: Programming Language :: Python :: 3.8
Classifier: Programming Language :: Python :: 3.9
Classifier: Programming Language :: Python :: 3.10
Classifier: Programming Language :: Python :: 3.11
Classifier: Topic :: Database
Requires-Dist: django (>=2.2)
Requires-Dist: marshmallow (>=3.0.3)
Requires-Dist: marshmallow-dataclass (>=7.0.0)
Project-URL: Repository, https://github.com/OJFord/marshmallow-dataclass-djangofield
